ctreport_selenium/__init__.py
ctreport_selenium/ctgeneratejsonfile.py
ctreport_selenium/ctlistener.py
ctreport_selenium/utility_classes.py
ctreport_selenium/ctreport_html/__init__.py
ctreport_selenium/ctreport_html/dashboard_view.py
ctreport_selenium/ctreport_html/detail_view.py
ctreport_selenium/ctreport_html/footer_view.py
ctreport_selenium/ctreport_html/html_report.py
ctreport_selenium/ctreport_html/properties.py
ctreport_selenium/ctreport_html/charts/__init__.py
ctreport_selenium/ctreport_html/charts/assertion.py
ctreport_selenium/ctreport_html/charts/priority.py
ctreport_selenium/ctreport_html/charts/status.py
ctreport_selenium/ctreport_html/charts/timeline.py
ctreport_selenium/ctreport_html/charts/verification.py
ctreport_selenium/ctreport_html/font/__init__.py
ctreport_selenium/ctreport_html/resource/__init__.py
ctreport_selenium/ctreport_html/scripts/__init__.py
ctreport_selenium/ctreport_html/scripts/detailmodal.py
ctreport_selenium/ctreport_html/scripts/filter.py
ctreport_selenium/ctreport_html/scripts/footer.py
ctreport_selenium/ctreport_html/scripts/imagemodal.py
ctreport_selenium/ctreport_html/scripts/search.py
ctreport_selenium/ctreport_html/scripts/toastr.py
ctreport_selenium/ctreport_html/scripts/toggle.py
ctreport_selenium/ctreport_html/scripts/tooltip.py
ctreport_selenium/ctreport_html/testdetail/__init__.py
ctreport_selenium/ctreport_html/testdetail/details.py
ctreport_selenium/ctreport_html/testdetail/summary.py
ctreport_selenium-1.1.4.dist-info/LICENSE.txt
ctreport_selenium-1.1.4.dist-info/METADATA
ctreport_selenium-1.1.4.dist-info/WHEEL
ctreport_selenium-1.1.4.dist-info/top_level.txt
ctreport_selenium-1.1.4.dist-info/RECORD
