Metadata-Version: 2.1
Name: ctreport-selenium
Version: 1.1.4
Summary: ctreport-selenium is a simple, creative and a customizable report for automation testing using Python. Best suitable for pytest, unit test and nose framework.
Home-page: https://naveens33.github.io/ctreport-selenium/
Author: Naveen.S
Author-email: naveensagayaselvaraj@gmail.com
License: MIT
Platform: UNKNOWN
Classifier: Programming Language :: Python :: 3
Classifier: License :: OSI Approved :: MIT License
Classifier: Operating System :: OS Independent
Requires-Python: >=3.6
